nlpls/__init__.py
nlpls-0.0.4.dist-info/METADATA
nlpls-0.0.4.dist-info/WHEEL
nlpls-0.0.4.dist-info/top_level.txt
nlpls-0.0.4.dist-info/RECORD
